lightningrobot_next/__init__.py
lightningrobot_next-0.0.1.dist-info/LICENSE
lightningrobot_next-0.0.1.dist-info/METADATA
lightningrobot_next-0.0.1.dist-info/WHEEL
lightningrobot_next-0.0.1.dist-info/top_level.txt
lightningrobot_next-0.0.1.dist-info/RECORD
