Metadata-Version: 2.1
Name: lightningrobot-next
Version: 0.0.1
Summary: 轻快，好用，基于Python的多平台机器人框架。
Author-email: Zhihan <zhihan2727@hotmail.com>
License: MIT License
Project-URL: Homepage, https://lightningrobot.github.io/
Project-URL: Documentation, https://lightningrobot.github.io/
Project-URL: Repository, https://github.com/LightningRobot/core.git
Project-URL: Bug Tracker, https://github.com/LightningRobot/core/issues
Keywords: robot,lightningrobot
Classifier: Development Status :: 3 - Alpha
Classifier: Programming Language :: Python
Requires-Python: >=3.8
License-File: LICENSE
